odoo8_addon_event_contact-8.0.1.0.0.99.dev3-py2.7-nspkg.pth
odoo_addons/event_contact/__openerp__.py
odoo_addons/event_contact/__init__.py
odoo_addons/event_contact/README.rst
odoo_addons/event_contact/models/__init__.py
odoo_addons/event_contact/models/event.py
odoo_addons/event_contact/i18n/es.po
odoo_addons/event_contact/views/event_event_view.xml
odoo_addons/event_contact/views/event_type_view.xml
odoo_addons/event_contact/tests/test_event.py
odoo_addons/event_contact/tests/__init__.py
odoo_addons/event_contact/static/description/icon.png
odoo8_addon_event_contact-8.0.1.0.0.99.dev3.dist-info/top_level.txt
odoo8_addon_event_contact-8.0.1.0.0.99.dev3.dist-info/WHEEL
odoo8_addon_event_contact-8.0.1.0.0.99.dev3.dist-info/RECORD
odoo8_addon_event_contact-8.0.1.0.0.99.dev3.dist-info/metadata.json
odoo8_addon_event_contact-8.0.1.0.0.99.dev3.dist-info/DESCRIPTION.rst
odoo8_addon_event_contact-8.0.1.0.0.99.dev3.dist-info/METADATA
odoo8_addon_event_contact-8.0.1.0.0.99.dev3.dist-info/namespace_packages.txt
